{
"meta":{"test_sets":[],"test_metrics":[],"learn_metrics":[{"best_value":"Min","name":"RMSE"}],"launch_mode":"Train","parameters":"","iteration_count":100,"learn_sets":["learn"],"name":"experiment"},
"iterations":[
{"learn":[1.377274799],"iteration":0,"passed_time":0.01147494669,"remaining_time":1.136019722},
{"learn":[1.374687434],"iteration":1,"passed_time":0.02136051428,"remaining_time":1.0466652},
{"learn":[1.372309439],"iteration":2,"passed_time":0.03156888056,"remaining_time":1.020727138},
{"learn":[1.370614088],"iteration":3,"passed_time":0.04132531201,"remaining_time":0.9918074883},
{"learn":[1.368837364],"iteration":4,"passed_time":0.05063842257,"remaining_time":0.9621300289},
{"learn":[1.367211763],"iteration":5,"passed_time":0.05988463436,"remaining_time":0.9381926049},
{"learn":[1.366114374],"iteration":6,"passed_time":0.069426414,"remaining_time":0.9223795002},
{"learn":[1.365020779],"iteration":7,"passed_time":0.0792056939,"remaining_time":0.9108654798},
{"learn":[1.364074417],"iteration":8,"passed_time":0.09093085199,"remaining_time":0.9194119479},
{"learn":[1.363219953],"iteration":9,"passed_time":0.1015382017,"remaining_time":0.9138438157},
{"learn":[1.362403641],"iteration":10,"passed_time":0.1110100363,"remaining_time":0.8981721117},
{"learn":[1.361713701],"iteration":11,"passed_time":0.1214615,"remaining_time":0.8907176665},
{"learn":[1.360943701],"iteration":12,"passed_time":0.1322308242,"remaining_time":0.8849293621},
{"learn":[1.360541969],"iteration":13,"passed_time":0.1418293911,"remaining_time":0.871237688},
{"learn":[1.360041938],"iteration":14,"passed_time":0.1524218212,"remaining_time":0.8637236535},
{"learn":[1.35960224],"iteration":15,"passed_time":0.1612862409,"remaining_time":0.8467527649},
{"learn":[1.35896587],"iteration":16,"passed_time":0.1728418903,"remaining_time":0.8438751113},
{"learn":[1.358646581],"iteration":17,"passed_time":0.1839855548,"remaining_time":0.8381564164},
{"learn":[1.358288418],"iteration":18,"passed_time":0.1930357244,"remaining_time":0.8229417724},
{"learn":[1.358030816],"iteration":19,"passed_time":0.2047891776,"remaining_time":0.8191567106},
{"learn":[1.357688394],"iteration":20,"passed_time":0.2149800934,"remaining_time":0.8087346372},
{"learn":[1.357432325],"iteration":21,"passed_time":0.2241910335,"remaining_time":0.7948591187},
{"learn":[1.357084398],"iteration":22,"passed_time":0.2365228307,"remaining_time":0.7918373028},
{"learn":[1.356672628],"iteration":23,"passed_time":0.2485124101,"remaining_time":0.7869559655},
{"learn":[1.356350953],"iteration":24,"passed_time":0.258462044,"remaining_time":0.7753861319},
{"learn":[1.356110578],"iteration":25,"passed_time":0.2692455563,"remaining_time":0.7663142756},
{"learn":[1.355892432],"iteration":26,"passed_time":0.2801154194,"remaining_time":0.757349097},
{"learn":[1.355636697],"iteration":27,"passed_time":0.2894933167,"remaining_time":0.7444113857},
{"learn":[1.3553768],"iteration":28,"passed_time":0.3016289458,"remaining_time":0.7384708673},
{"learn":[1.35518988],"iteration":29,"passed_time":0.3126897648,"remaining_time":0.7296094513},
{"learn":[1.354952668],"iteration":30,"passed_time":0.3246572581,"remaining_time":0.7226242197},
{"learn":[1.354742448],"iteration":31,"passed_time":0.3397249095,"remaining_time":0.7219154326},
{"learn":[1.354551293],"iteration":32,"passed_time":0.3528651567,"remaining_time":0.716423197},
{"learn":[1.354403067],"iteration":33,"passed_time":0.366017957,"remaining_time":0.710505446},
{"learn":[1.354172306],"iteration":34,"passed_time":0.383459884,"remaining_time":0.7121397845},
{"learn":[1.353767679],"iteration":35,"passed_time":0.4057081055,"remaining_time":0.7212588543},
{"learn":[1.353599693],"iteration":36,"passed_time":0.4172073426,"remaining_time":0.7103800699},
{"learn":[1.353429266],"iteration":37,"passed_time":0.4311486868,"remaining_time":0.7034531206},
{"learn":[1.353254379],"iteration":38,"passed_time":0.4416474863,"remaining_time":0.6907819658},
{"learn":[1.353010691],"iteration":39,"passed_time":0.4545584638,"remaining_time":0.6818376958},
{"learn":[1.352850897],"iteration":40,"passed_time":0.4662886261,"remaining_time":0.6710007059},
{"learn":[1.352678017],"iteration":41,"passed_time":0.4786835442,"remaining_time":0.6610391801},
{"learn":[1.352539257],"iteration":42,"passed_time":0.4890536159,"remaining_time":0.6482803746},
{"learn":[1.352376539],"iteration":43,"passed_time":0.5004912905,"remaining_time":0.6369889151},
{"learn":[1.352166334],"iteration":44,"passed_time":0.5133423112,"remaining_time":0.6274183804},
{"learn":[1.352077943],"iteration":45,"passed_time":0.523646289,"remaining_time":0.6147152089},
{"learn":[1.351856411],"iteration":46,"passed_time":0.5346409608,"remaining_time":0.6028929984},
{"learn":[1.351652145],"iteration":47,"passed_time":0.5466074439,"remaining_time":0.5921580642},
{"learn":[1.351579209],"iteration":48,"passed_time":0.558881385,"remaining_time":0.5816928701},
{"learn":[1.351401762],"iteration":49,"passed_time":0.5711721018,"remaining_time":0.5711721018},
{"learn":[1.351290065],"iteration":50,"passed_time":0.5847004706,"remaining_time":0.5617710404},
{"learn":[1.351119992],"iteration":51,"passed_time":0.5972806277,"remaining_time":0.5513359641},
{"learn":[1.350961225],"iteration":52,"passed_time":0.6252634463,"remaining_time":0.5544789052},
{"learn":[1.350743087],"iteration":53,"passed_time":0.6801809692,"remaining_time":0.5794134182},
{"learn":[1.350640922],"iteration":54,"passed_time":0.7189578327,"remaining_time":0.5882382268},
{"learn":[1.350522107],"iteration":55,"passed_time":0.7576901512,"remaining_time":0.5953279759},
{"learn":[1.350379499],"iteration":56,"passed_time":0.7852879337,"remaining_time":0.5924101956},
{"learn":[1.350254907],"iteration":57,"passed_time":0.798720572,"remaining_time":0.5783838625},
{"learn":[1.3501683],"iteration":58,"passed_time":0.8129028044,"remaining_time":0.564898559},
{"learn":[1.350055689],"iteration":59,"passed_time":0.8437994105,"remaining_time":0.5625329404},
{"learn":[1.349941566],"iteration":60,"passed_time":0.8560764909,"remaining_time":0.5473275925},
{"learn":[1.349863408],"iteration":61,"passed_time":0.8661059204,"remaining_time":0.5308391125},
{"learn":[1.34975385],"iteration":62,"passed_time":0.8780000342,"remaining_time":0.5156508137},
{"learn":[1.349520003],"iteration":63,"passed_time":0.8885830816,"remaining_time":0.4998279834},
{"learn":[1.349425037],"iteration":64,"passed_time":0.8985790172,"remaining_time":0.48385024},
{"learn":[1.349302486],"iteration":65,"passed_time":0.9098112752,"remaining_time":0.4686906569},
{"learn":[1.349138567],"iteration":66,"passed_time":0.9219136307,"remaining_time":0.4540768629},
{"learn":[1.349005259],"iteration":67,"passed_time":0.9329554046,"remaining_time":0.4390378374},
{"learn":[1.348819303],"iteration":68,"passed_time":0.9448774024,"remaining_time":0.4245101373},
{"learn":[1.348759009],"iteration":69,"passed_time":0.9573360552,"remaining_time":0.4102868808},
{"learn":[1.348603695],"iteration":70,"passed_time":0.9693251468,"remaining_time":0.3959215388},
{"learn":[1.348495957],"iteration":71,"passed_time":0.9801127816,"remaining_time":0.3811549706},
{"learn":[1.348382131],"iteration":72,"passed_time":0.9916368834,"remaining_time":0.3667698062},
{"learn":[1.348284846],"iteration":73,"passed_time":1.002764399,"remaining_time":0.3523226265},
{"learn":[1.348184818],"iteration":74,"passed_time":1.014754654,"remaining_time":0.3382515513},
{"learn":[1.348093848],"iteration":75,"passed_time":1.026517422,"remaining_time":0.3241633964},
{"learn":[1.34799256],"iteration":76,"passed_time":1.037498537,"remaining_time":0.3099021605},
{"learn":[1.34783153],"iteration":77,"passed_time":1.047759429,"remaining_time":0.2955218901},
{"learn":[1.347725378],"iteration":78,"passed_time":1.059173168,"remaining_time":0.2815523612},
{"learn":[1.347633093],"iteration":79,"passed_time":1.071943785,"remaining_time":0.2679859461},
{"learn":[1.347535772],"iteration":80,"passed_time":1.083242909,"remaining_time":0.2540940156},
{"learn":[1.347423735],"iteration":81,"passed_time":1.094762763,"remaining_time":0.2403137772},
{"learn":[1.347297273],"iteration":82,"passed_time":1.105855582,"remaining_time":0.226500541},
{"learn":[1.347200933],"iteration":83,"passed_time":1.118930779,"remaining_time":0.2131296721},
{"learn":[1.34706667],"iteration":84,"passed_time":1.130302561,"remaining_time":0.1994651579},
{"learn":[1.346959721],"iteration":85,"passed_time":1.141710626,"remaining_time":0.1858598693},
{"learn":[1.34681024],"iteration":86,"passed_time":1.153103432,"remaining_time":0.1723028117},
{"learn":[1.346651081],"iteration":87,"passed_time":1.162389419,"remaining_time":0.158507648},
{"learn":[1.346575747],"iteration":88,"passed_time":1.174065802,"remaining_time":0.1451092564},
{"learn":[1.346519447],"iteration":89,"passed_time":1.18643583,"remaining_time":0.1318262033},
{"learn":[1.346411638],"iteration":90,"passed_time":1.197443156,"remaining_time":0.118428444},
{"learn":[1.346332515],"iteration":91,"passed_time":1.207010125,"remaining_time":0.1049574022},
{"learn":[1.346195533],"iteration":92,"passed_time":1.218132184,"remaining_time":0.09168736866},
{"learn":[1.346102563],"iteration":93,"passed_time":1.228307376,"remaining_time":0.07840259845},
{"learn":[1.34598299],"iteration":94,"passed_time":1.239923505,"remaining_time":0.06525913186},
{"learn":[1.34592313],"iteration":95,"passed_time":1.251978388,"remaining_time":0.05216576617},
{"learn":[1.345814723],"iteration":96,"passed_time":1.263554117,"remaining_time":0.0390789933},
{"learn":[1.345736495],"iteration":97,"passed_time":1.272700058,"remaining_time":0.02597347057},
{"learn":[1.345620332],"iteration":98,"passed_time":1.284451069,"remaining_time":0.01297425322},
{"learn":[1.345486334],"iteration":99,"passed_time":1.293305619,"remaining_time":0}
]}